LICENSE
MANIFEST.in
README.rst
setup.cfg
setup.py
SimpleConfigParser.egg-info/PKG-INFO
SimpleConfigParser.egg-info/SOURCES.txt
SimpleConfigParser.egg-info/dependency_links.txt
SimpleConfigParser.egg-info/top_level.txt
SimpleConfigParser.egg-info/zip-safe
simpleconfigparser/__init__.py
tests/__init__.py
tests/test_simpleconfigparser.py