Metadata-Version: 1.0
Name: SimpleConfigParser
Version: 0.1.0
Summary: Simplifies and enchances functionalities in Python's ConfigParser
Home-page: http://github.com/helgi/python-simpleconfigparser
Author: Helgi Þorbjörnsson
Author-email: helgi@php.net
License: MIT License
Keywords: ConfiParser,ini
Platform: any
Classifier: Development Status :: 3 - Alpha
Classifier: Intended Audience :: Developers
Classifier: Topic :: Utilities
Classifier: License :: OSI Approved :: MIT License
Classifier: Programming Language :: Python
Classifier: Programming Language :: Python :: 2.6
Classifier: Programming Language :: Python :: 2.7
Classifier: Programming Language :: Python :: 3.2
Classifier: Programming Language :: Python :: 3.3
